MANIFEST.in
README.rst
setup.cfg
setup.py
aio_crud_store/__init__.py
aio_crud_store/aiopg_store.py
aio_crud_store/base_store.py
aio_crud_store/motor_store.py
aio_crud_store.egg-info/PKG-INFO
aio_crud_store.egg-info/SOURCES.txt
aio_crud_store.egg-info/dependency_links.txt
aio_crud_store.egg-info/top_level.txt
examples/aiopg_example.py
examples/bench.py
examples/motor_example.py