Metadata-Version: 1.1
Name: aio-crud-store
Version: 0.0.2
Summary: A small subset of dbs capabilities to write dbs-independent asyncio libs
Home-page: https://github.com/imbolc/aio_crud_store
Author: Imbolc
Author-email: imbolc@imbolc.name
License: ISC
Platform: UNKNOWN
Classifier: License :: OSI Approved :: ISC License (ISCL)
Classifier: Intended Audience :: Developers
Classifier: Programming Language :: Python
Classifier: Programming Language :: Python :: 3
Classifier: Programming Language :: Python :: 3.5
Classifier: Topic :: Database
